carnegie/__init__.py
carnegie-0.0.1.dist-info/METADATA
carnegie-0.0.1.dist-info/WHEEL
carnegie-0.0.1.dist-info/entry_points.txt
carnegie-0.0.1.dist-info/RECORD
