Metadata-Version: 2.4
Name: carnegie
Version: 0.0.1
Summary: Library management
Author-email: Hector Munoz <hectormz.git@gmail.com>
Requires-Python: >=3.12
